aton/__init__.py
aton/decoder.py
aton/encoder.py
aton/version.py
aton_format-1.0.2.dist-info/licenses/LICENSE
aton_format-1.0.2.dist-info/METADATA
aton_format-1.0.2.dist-info/WHEEL
aton_format-1.0.2.dist-info/top_level.txt
aton_format-1.0.2.dist-info/RECORD
