Metadata-Version: 2.4
Name: aton-format
Version: 1.0.2
Summary: ATON FORMAT - Adaptive Token-Oriented Notation - Data format optimized for LLMs with 56% token reduction
Home-page: https://www.atonformat.com
Author: Stefano D'Agostino
Author-email: Stefano D'Agostino <dago.stefano@gmail.com>
Maintainer-email: Stefano D'Agostino <dago.stefano@gmail.com>
License: MIT
Project-URL: Homepage, https://www.atonformat.com
Project-URL: Documentation, https://www.atonformat.com/documentation.html
Project-URL: Repository, https://github.com/dagoSte/aton-format
Keywords: aton,llm,token-optimization,data-format,serialization,json-alternative,gpt,claude,ai,machine-learning
Classifier: Development Status :: 4 - Beta
Classifier: Intended Audience :: Developers
Classifier: Intended Audience :: Science/Research
Classifier: License :: OSI Approved :: MIT License
Classifier: Programming Language :: Python :: 3
Classifier: Programming Language :: Python :: 3.8
Classifier: Programming Language :: Python :: 3.9
Classifier: Programming Language :: Python :: 3.10
Classifier: Programming Language :: Python :: 3.11
Classifier: Programming Language :: Python :: 3.12
Classifier: Topic :: Software Development :: Libraries :: Python Modules
Classifier: Topic :: Scientific/Engineering :: Artificial Intelligence
Classifier: Topic :: Text Processing :: General
Requires-Python: >=3.8
License-File: LICENSE
Provides-Extra: dev
Requires-Dist: pytest>=7.0; extra == "dev"
Requires-Dist: pytest-cov>=4.0; extra == "dev"
Requires-Dist: black>=23.0; extra == "dev"
Requires-Dist: flake8>=6.0; extra == "dev"
Requires-Dist: mypy>=1.0; extra == "dev"
Dynamic: author
Dynamic: home-page
Dynamic: license-file
Dynamic: requires-python
